MANIFEST.in
README.txt
setup.cfg
setup.py
docs/HISTORY.txt
docs/INSTALL.txt
docs/LICENSE.GPL
docs/LICENSE.txt
src/collective/__init__.py
src/collective.alias.egg-info/PKG-INFO
src/collective.alias.egg-info/SOURCES.txt
src/collective.alias.egg-info/dependency_links.txt
src/collective.alias.egg-info/entry_points.txt
src/collective.alias.egg-info/namespace_packages.txt
src/collective.alias.egg-info/not-zip-safe
src/collective.alias.egg-info/requires.txt
src/collective.alias.egg-info/top_level.txt
src/collective/alias/TODO.txt
src/collective/alias/__init__.py
src/collective/alias/annotations.py
src/collective/alias/browser.py
src/collective/alias/configure.zcml
src/collective/alias/content.py
src/collective/alias/events.py
src/collective/alias/info.py
src/collective/alias/interfaces.py
src/collective/alias/paste.py
src/collective/alias/upgrade.py
src/collective/alias/vocabulary.py
src/collective/alias/browser_templates/contentviews.pt
src/collective/alias/locales/collective.alias.pot
src/collective/alias/locales/fr/LC_MESSAGES/collective.alias.mo
src/collective/alias/locales/fr/LC_MESSAGES/collective.alias.po
src/collective/alias/profiles/default/actionicons.xml
src/collective/alias/profiles/default/actions.xml
src/collective/alias/profiles/default/metadata.xml
src/collective/alias/profiles/default/registry.xml
src/collective/alias/profiles/default/rolemap.xml
src/collective/alias/profiles/default/types.xml
src/collective/alias/profiles/default/types/collective.alias.xml
src/collective/alias/static/alias.gif
src/collective/alias/tests/__init__.py
src/collective/alias/tests/layer.py
src/collective/alias/tests/test_aliasing.py
src/collective/alias/tests/test_info.py
src/collective/alias/tests/test_paste.py
src/collective/alias/tests/test_setup.py