Metadata-Version: 1.0
Name: collective.alias
Version: 1.3
Summary: Aliasing of Plone content
Home-page: http://pypi.python.org/pypi/collective.alias
Author: Martin Aspeli
Author-email: optilude@gmail.com
License: GPL
Keywords: plone alias
Platform: UNKNOWN
Classifier: Framework :: Plone
Classifier: Programming Language :: Python
Classifier: Topic :: Software Development :: Libraries :: Python Modules
